{
    "section1": {
        "files": [
            {
                "url": "assets/Seasonal Tilesets/1 - Grassland/Background parts/_Complete_static_BG_(288 x 208).png",
                "frameConfig": {
                    "frameWidth": 32,
                    "frameHeight": 32,
                    "startFrame": 0,
                    "endFrame": -1,
                    "spacing": 0,
                    "margin": 0
                },
                "type": "spritesheet",
                "key": "_Complete_static_BG_(288 x 208)"
            },
            {
                "url": "assets/Seasonal Tilesets/2 - Autumn Forest/Background parts/_Complete_static_BG_(288 x 208).png",
                "frameConfig": {
                    "frameWidth": 32,
                    "frameHeight": 32,
                    "startFrame": 0,
                    "endFrame": -1,
                    "spacing": 0,
                    "margin": 0
                },
                "type": "spritesheet",
                "key": "_Complete_static_BG_(288 x 208)_1"
            },
            {
                "url": "assets/Seasonal Tilesets/3 - Tropics/Background parts/_Complete_static_BG_(288 x 208).png",
                "frameConfig": {
                    "frameWidth": 32,
                    "frameHeight": 32,
                    "startFrame": 0,
                    "endFrame": -1,
                    "spacing": 0,
                    "margin": 0
                },
                "type": "spritesheet",
                "key": "_Complete_static_BG_(288 x 208)_2"
            },
            {
                "url": "assets/Seasonal Tilesets/4 - Winter World/Background parts/_Complete_static_BG_(288 x 208).png",
                "frameConfig": {
                    "frameWidth": 32,
                    "frameHeight": 32,
                    "startFrame": 0,
                    "endFrame": -1,
                    "spacing": 0,
                    "margin": 0
                },
                "type": "spritesheet",
                "key": "_Complete_static_BG_(288 x 208)_3"
            },
            {
                "url": "assets/Seasonal Tileset/1 - Grassland/Background parts/_Complete_static_BG_(288 x 208).png",
                "type": "image",
                "key": "_Complete_static_BG_(288 x 208)_4"
            },
            {
                "url": "assets/Seasonal Tileset/2 - Autumn Forest/Background parts/_Complete_static_BG_(288 x 208).png",
                "type": "image",
                "key": "_Complete_static_BG_(288 x 208)_5"
            },
            {
                "url": "assets/Seasonal Tileset/3 - Tropics/Background parts/_Complete_static_BG_(288 x 208).png",
                "type": "image",
                "key": "_Complete_static_BG_(288 x 208)_6"
            },
            {
                "url": "assets/Seasonal Tileset/4 - Winter World/Background parts/_Complete_static_BG_(288 x 208).png",
                "type": "image",
                "key": "_Complete_static_BG_(288 x 208)_7"
            },
            {
                "url": "assets/Seasonal Tilesets/1 - Grassland/Background parts/1 - Foreground_scenery.png",
                "frameConfig": {
                    "frameWidth": 32,
                    "frameHeight": 32,
                    "startFrame": 0,
                    "endFrame": -1,
                    "spacing": 0,
                    "margin": 0
                },
                "type": "spritesheet",
                "key": "1 - Foreground_scenery"
            },
            {
                "url": "assets/Seasonal Tilesets/1 - Grassland/Background parts/1 - Foreground_scenery.png",
                "type": "image",
                "key": "1 - Foreground_scenery_1"
            },
            {
                "url": "assets/Seasonal Tileset/1 - Grassland/Background parts/1 - Foreground_scenery.png",
                "type": "image",
                "key": "1 - Foreground_scenery_2"
            },
            {
                "url": "assets/Seasonal Tilesets/2 - Autumn Forest/Background parts/1 - Leaf_top.png",
                "frameConfig": {
                    "frameWidth": 32,
                    "frameHeight": 32,
                    "startFrame": 0,
                    "endFrame": -1,
                    "spacing": 0,
                    "margin": 0
                },
                "type": "spritesheet",
                "key": "1 - Leaf_top"
            },
            {
                "url": "assets/Seasonal Tileset/2 - Autumn Forest/Background parts/1 - Leaf_top.png",
                "type": "image",
                "key": "1 - Leaf_top_1"
            },
            {
                "url": "assets/Seasonal Tilesets/4 - Winter World/Background parts/1 - Snowy_foreground_area.png",
                "frameConfig": {
                    "frameWidth": 32,
                    "frameHeight": 32,
                    "startFrame": 0,
                    "endFrame": -1,
                    "spacing": 0,
                    "margin": 0
                },
                "type": "spritesheet",
                "key": "1 - Snowy_foreground_area"
            },
            {
                "url": "assets/Seasonal Tileset/4 - Winter World/Background parts/1 - Snowy_foreground_area.png",
                "type": "image",
                "key": "1 - Snowy_foreground_area_1"
            },
            {
                "url": "assets/Seasonal Tileset/3 - Tropics/Background parts/1 - Waters_version_1.png",
                "type": "image",
                "key": "1 - Waters_version"
            },
            {
                "url": "assets/Seasonal Tilesets/3 - Tropics/Background parts/1 - Waters_version_1.png",
                "frameConfig": {
                    "frameWidth": 32,
                    "frameHeight": 32,
                    "startFrame": 0,
                    "endFrame": -1,
                    "spacing": 0,
                    "margin": 0
                },
                "type": "spritesheet",
                "key": "1 - Waters_version_1"
            },
            {
                "url": "assets/Seasonal Tilesets/1 - Grassland/Background parts/2 - Hills.png",
                "frameConfig": {
                    "frameWidth": 32,
                    "frameHeight": 32,
                    "startFrame": 0,
                    "endFrame": -1,
                    "spacing": 0,
                    "margin": 0
                },
                "type": "spritesheet",
                "key": "2 - Hills"
            },
            {
                "url": "assets/Seasonal Tileset/1 - Grassland/Background parts/2 - Hills.png",
                "type": "image",
                "key": "2 - Hills_1"
            },
            {
                "url": "assets/Seasonal Tilesets/4 - Winter World/Background parts/2 - Smaller_mountains.png",
                "frameConfig": {
                    "frameWidth": 32,
                    "frameHeight": 32,
                    "startFrame": 0,
                    "endFrame": -1,
                    "spacing": 0,
                    "margin": 0
                },
                "type": "spritesheet",
                "key": "2 - Smaller_mountains"
            },
            {
                "url": "assets/Seasonal Tileset/4 - Winter World/Background parts/2 - Smaller_mountains.png",
                "type": "image",
                "key": "2 - Smaller_mountains_1"
            },
            {
                "url": "assets/Seasonal Tilesets/2 - Autumn Forest/Background parts/2 - Trees.png",
                "frameConfig": {
                    "frameWidth": 32,
                    "frameHeight": 32,
                    "startFrame": 0,
                    "endFrame": -1,
                    "spacing": 0,
                    "margin": 0
                },
                "type": "spritesheet",
                "key": "2 - Trees"
            },
            {
                "url": "assets/Seasonal Tileset/2 - Autumn Forest/Background parts/2 - Trees.png",
                "type": "image",
                "key": "2 - Trees_1"
            },
            {
                "url": "assets/Seasonal Tileset/3 - Tropics/Background parts/2 - Waters_version_2.png",
                "type": "image",
                "key": "2 - Waters_version"
            },
            {
                "url": "assets/Seasonal Tilesets/3 - Tropics/Background parts/2 - Waters_version_2.png",
                "frameConfig": {
                    "frameWidth": 32,
                    "frameHeight": 32,
                    "startFrame": 0,
                    "endFrame": -1,
                    "spacing": 0,
                    "margin": 0
                },
                "type": "spritesheet",
                "key": "2 - Waters_version_2"
            },
            {
                "url": "assets/Seasonal Tilesets/4 - Winter World/Background parts/3 - Big_mountain_BG.png",
                "frameConfig": {
                    "frameWidth": 32,
                    "frameHeight": 32,
                    "startFrame": 0,
                    "endFrame": -1,
                    "spacing": 0,
                    "margin": 0
                },
                "type": "spritesheet",
                "key": "3 - Big_mountain_BG"
            },
            {
                "url": "assets/Seasonal Tileset/4 - Winter World/Background parts/3 - Big_mountain_BG.png",
                "type": "image",
                "key": "3 - Big_mountain_BG_1"
            },
            {
                "url": "assets/Seasonal Tilesets/2 - Autumn Forest/Background parts/3 - Bottom_leaf_piles.png",
                "frameConfig": {
                    "frameWidth": 32,
                    "frameHeight": 32,
                    "startFrame": 0,
                    "endFrame": -1,
                    "spacing": 0,
                    "margin": 0
                },
                "type": "spritesheet",
                "key": "3 - Bottom_leaf_piles"
            },
            {
                "url": "assets/Seasonal Tileset/2 - Autumn Forest/Background parts/3 - Bottom_leaf_piles.png",
                "type": "image",
                "key": "3 - Bottom_leaf_piles_1"
            },
            {
                "url": "assets/Seasonal Tileset/1 - Grassland/Background parts/3 - Cloud_cover_1.png",
                "type": "image",
                "key": "3 - Cloud_cover"
            },
            {
                "url": "assets/Seasonal Tilesets/1 - Grassland/Background parts/3 - Cloud_cover_1.png",
                "frameConfig": {
                    "frameWidth": 32,
                    "frameHeight": 32,
                    "startFrame": 0,
                    "endFrame": -1,
                    "spacing": 0,
                    "margin": 0
                },
                "type": "spritesheet",
                "key": "3 - Cloud_cover_1"
            },
            {
                "url": "assets/Seasonal Tilesets/3 - Tropics/Background parts/3 - Floating_clouds.png",
                "frameConfig": {
                    "frameWidth": 32,
                    "frameHeight": 32,
                    "startFrame": 0,
                    "endFrame": -1,
                    "spacing": 0,
                    "margin": 0
                },
                "type": "spritesheet",
                "key": "3 - Floating_clouds"
            },
            {
                "url": "assets/Seasonal Tileset/3 - Tropics/Background parts/3 - Floating_clouds.png",
                "type": "image",
                "key": "3 - Floating_clouds_1"
            },
            {
                "url": "assets/Seasonal Tilesets/3 - Tropics/Background parts/4 - Background_clouds.png",
                "frameConfig": {
                    "frameWidth": 32,
                    "frameHeight": 32,
                    "startFrame": 0,
                    "endFrame": -1,
                    "spacing": 0,
                    "margin": 0
                },
                "type": "spritesheet",
                "key": "4 - Background_clouds"
            },
            {
                "url": "assets/Seasonal Tileset/3 - Tropics/Background parts/4 - Background_clouds.png",
                "type": "image",
                "key": "4 - Background_clouds_1"
            },
            {
                "url": "assets/Seasonal Tileset/1 - Grassland/Background parts/4 - Cloud_cover_2.png",
                "type": "image",
                "key": "4 - Cloud_cover"
            },
            {
                "url": "assets/Seasonal Tilesets/1 - Grassland/Background parts/4 - Cloud_cover_2.png",
                "frameConfig": {
                    "frameWidth": 32,
                    "frameHeight": 32,
                    "startFrame": 0,
                    "endFrame": -1,
                    "spacing": 0,
                    "margin": 0
                },
                "type": "spritesheet",
                "key": "4 - Cloud_cover_2"
            },
            {
                "url": "assets/Seasonal Tileset/2 - Autumn Forest/Background parts/4 - Tree_row_BG_1.png",
                "type": "image",
                "key": "4 - Tree_row_BG"
            },
            {
                "url": "assets/Seasonal Tilesets/2 - Autumn Forest/Background parts/4 - Tree_row_BG_1.png",
                "frameConfig": {
                    "frameWidth": 32,
                    "frameHeight": 32,
                    "startFrame": 0,
                    "endFrame": -1,
                    "spacing": 0,
                    "margin": 0
                },
                "type": "spritesheet",
                "key": "4 - Tree_row_BG_1"
            },
            {
                "url": "assets/Seasonal Tilesets/1 - Grassland/Background parts/5 - Sky_color.png",
                "frameConfig": {
                    "frameWidth": 32,
                    "frameHeight": 32,
                    "startFrame": 0,
                    "endFrame": -1,
                    "spacing": 0,
                    "margin": 0
                },
                "type": "spritesheet",
                "key": "5 - Sky_color"
            },
            {
                "url": "assets/Seasonal Tilesets/3 - Tropics/Background parts/5 - Sky_color.png",
                "frameConfig": {
                    "frameWidth": 32,
                    "frameHeight": 32,
                    "startFrame": 0,
                    "endFrame": -1,
                    "spacing": 0,
                    "margin": 0
                },
                "type": "spritesheet",
                "key": "5 - Sky_color_1"
            },
            {
                "url": "assets/Seasonal Tileset/1 - Grassland/Background parts/5 - Sky_color.png",
                "type": "image",
                "key": "5 - Sky_color_2"
            },
            {
                "url": "assets/Seasonal Tileset/3 - Tropics/Background parts/5 - Sky_color.png",
                "type": "image",
                "key": "5 - Sky_color_3"
            },
            {
                "url": "assets/Seasonal Tileset/2 - Autumn Forest/Background parts/5 - Tree_row_BG_2.png",
                "type": "image",
                "key": "5 - Tree_row_BG"
            },
            {
                "url": "assets/Seasonal Tilesets/2 - Autumn Forest/Background parts/5 - Tree_row_BG_2.png",
                "frameConfig": {
                    "frameWidth": 32,
                    "frameHeight": 32,
                    "startFrame": 0,
                    "endFrame": -1,
                    "spacing": 0,
                    "margin": 0
                },
                "type": "spritesheet",
                "key": "5 - Tree_row_BG_2"
            },
            {
                "url": "assets/Seasonal Tilesets/2 - Autumn Forest/Background parts/6 - Distant_trees.png",
                "frameConfig": {
                    "frameWidth": 32,
                    "frameHeight": 32,
                    "startFrame": 0,
                    "endFrame": -1,
                    "spacing": 0,
                    "margin": 0
                },
                "type": "spritesheet",
                "key": "6 - Distant_trees"
            },
            {
                "url": "assets/Seasonal Tileset/2 - Autumn Forest/Background parts/6 - Distant_trees.png",
                "type": "image",
                "key": "6 - Distant_trees_1"
            },
            {
                "url": "assets/Seasonal Tilesets/2 - Autumn Forest/Autumn_entities (16 x 16).png",
                "frameConfig": {
                    "frameWidth": 32,
                    "frameHeight": 32,
                    "startFrame": 0,
                    "endFrame": -1,
                    "spacing": 0,
                    "margin": 0
                },
                "type": "spritesheet",
                "key": "Autumn_entities (16 x 16)"
            },
            {
                "url": "assets/Seasonal Tileset/2 - Autumn Forest/Autumn_entities (16 x 16).png",
                "type": "image",
                "key": "Autumn_entities (16 x 16)_1"
            },
            {
                "url": "assets/kenny platformer art/Backgrounds/backgrounds.png",
                "frameConfig": {
                    "frameWidth": 32,
                    "frameHeight": 32,
                    "startFrame": 0,
                    "endFrame": -1,
                    "spacing": 0,
                    "margin": 0
                },
                "type": "spritesheet",
                "key": "backgrounds"
            },
            {
                "url": "assets/kenny art/Backgrounds/backgrounds.png",
                "type": "image",
                "key": "backgrounds_1"
            },
            {
                "url": "assets/Seasonal Tilesets/5 - Misc. universal tiles/Blocks (16 x 16).png",
                "frameConfig": {
                    "frameWidth": 32,
                    "frameHeight": 32,
                    "startFrame": 0,
                    "endFrame": -1,
                    "spacing": 0,
                    "margin": 0
                },
                "type": "spritesheet",
                "key": "Blocks (16 x 16)"
            },
            {
                "url": "assets/Seasonal Tileset/5 - Misc. universal tiles/Blocks (16 x 16).png",
                "type": "image",
                "key": "Blocks (16 x 16)_1"
            },
            {
                "url": "assets/Seasonal Tilesets/5 - Misc. universal tiles/Bubbling_Oil_frames (16 x 32).png",
                "frameConfig": {
                    "frameWidth": 32,
                    "frameHeight": 32,
                    "startFrame": 0,
                    "endFrame": -1,
                    "spacing": 0,
                    "margin": 0
                },
                "type": "spritesheet",
                "key": "Bubbling_Oil_frames (16 x 32)"
            },
            {
                "url": "assets/Seasonal Tileset/5 - Misc. universal tiles/Bubbling_Oil_frames (16 x 32).png",
                "type": "image",
                "key": "Bubbling_Oil_frames (16 x 32)_1"
            },
            {
                "url": "assets/dino.png",
                "key": "dino",
                "type": "image"
            },
            {
                "url": "assets/Seasonal Tilesets/1 - Grassland/Extra_plants (16 x 16).png",
                "frameConfig": {
                    "frameWidth": 32,
                    "frameHeight": 32,
                    "startFrame": 0,
                    "endFrame": -1,
                    "spacing": 0,
                    "margin": 0
                },
                "type": "spritesheet",
                "key": "Extra_plants (16 x 16)"
            },
            {
                "url": "assets/Seasonal Tileset/1 - Grassland/Extra_plants (16 x 16).png",
                "type": "image",
                "key": "Extra_plants (16 x 16)_1"
            },
            {
                "url": "assets/FinnSprite.png",
                "frameConfig": {
                    "frameWidth": 32,
                    "frameHeight": 32,
                    "startFrame": 0,
                    "endFrame": -1,
                    "spacing": 0,
                    "margin": 0
                },
                "type": "spritesheet",
                "key": "FinnSprite"
            },
            {
                "url": "assets/Seasonal Tilesets/5 - Misc. universal tiles/Flowers (16 x 16).png",
                "frameConfig": {
                    "frameWidth": 32,
                    "frameHeight": 32,
                    "startFrame": 0,
                    "endFrame": -1,
                    "spacing": 0,
                    "margin": 0
                },
                "type": "spritesheet",
                "key": "Flowers (16 x 16)"
            },
            {
                "url": "assets/Seasonal Tileset/5 - Misc. universal tiles/Flowers (16 x 16).png",
                "type": "image",
                "key": "Flowers (16 x 16)_1"
            },
            {
                "url": "assets/Seasonal Tilesets/1 - Grassland/Grassland_entities (16 x 16).png",
                "frameConfig": {
                    "frameWidth": 64,
                    "frameHeight": 64,
                    "startFrame": 0,
                    "endFrame": -1,
                    "spacing": 0,
                    "margin": 0
                },
                "type": "spritesheet",
                "key": "Grassland_entities (16 x 16)"
            },
            {
                "url": "assets/Seasonal Tileset/1 - Grassland/Grassland_entities (16 x 16).png",
                "type": "image",
                "key": "Grassland_entities (16 x 16)_1"
            },
            {
                "url": "assets/Seasonal Tilesets/5 - Misc. universal tiles/House (112 x 96).png",
                "frameConfig": {
                    "frameWidth": 32,
                    "frameHeight": 32,
                    "startFrame": 0,
                    "endFrame": -1,
                    "spacing": 0,
                    "margin": 0
                },
                "type": "spritesheet",
                "key": "House (112 x 96)"
            },
            {
                "url": "assets/Seasonal Tileset/5 - Misc. universal tiles/House (112 x 96).png",
                "type": "image",
                "key": "House (112 x 96)_1"
            },
            {
                "url": "assets/Seasonal Tilesets/5 - Misc. universal tiles/Lava_frames (16 x 32).png",
                "frameConfig": {
                    "frameWidth": 32,
                    "frameHeight": 32,
                    "startFrame": 0,
                    "endFrame": -1,
                    "spacing": 0,
                    "margin": 0
                },
                "type": "spritesheet",
                "key": "Lava_frames (16 x 32)"
            },
            {
                "url": "assets/Seasonal Tileset/5 - Misc. universal tiles/Lava_frames (16 x 32).png",
                "type": "image",
                "key": "Lava_frames (16 x 32)_1"
            },
            {
                "url": "assets/Seasonal Tilesets/5 - Misc. universal tiles/Metal_Wire_fence (16 x 16).png",
                "frameConfig": {
                    "frameWidth": 32,
                    "frameHeight": 32,
                    "startFrame": 0,
                    "endFrame": -1,
                    "spacing": 0,
                    "margin": 0
                },
                "type": "spritesheet",
                "key": "Metal_Wire_fence (16 x 16)"
            },
            {
                "url": "assets/Seasonal Tileset/5 - Misc. universal tiles/Metal_Wire_fence (16 x 16).png",
                "type": "image",
                "key": "Metal_Wire_fence (16 x 16)_1"
            },
            {
                "url": "assets/plastic bag.png",
                "type": "image",
                "key": "plastic bag"
            },
            {
                "url": "assets/Seasonal Tilesets/5 - Misc. universal tiles/Rock_shape (16 x 16).png",
                "frameConfig": {
                    "frameWidth": 32,
                    "frameHeight": 32,
                    "startFrame": 0,
                    "endFrame": -1,
                    "spacing": 0,
                    "margin": 0
                },
                "type": "spritesheet",
                "key": "Rock_shape (16 x 16)"
            },
            {
                "url": "assets/Seasonal Tileset/5 - Misc. universal tiles/Rock_shape (16 x 16).png",
                "type": "image",
                "key": "Rock_shape (16 x 16)_1"
            },
            {
                "url": "assets/kenny platformer art/Sample.png",
                "frameConfig": {
                    "frameWidth": 32,
                    "frameHeight": 32,
                    "startFrame": 0,
                    "endFrame": -1,
                    "spacing": 0,
                    "margin": 0
                },
                "type": "spritesheet",
                "key": "Sample"
            },
            {
                "url": "assets/kenny art/Sample.png",
                "type": "image",
                "key": "Sample_1"
            },
            {
                "url": "assets/Seasonal Tilesets/5 - Misc. universal tiles/Snack_machine_Bench_Trash_bin (16 x 16).png",
                "frameConfig": {
                    "frameWidth": 32,
                    "frameHeight": 32,
                    "startFrame": 0,
                    "endFrame": -1,
                    "spacing": 0,
                    "margin": 0
                },
                "type": "spritesheet",
                "key": "Snack_machine_Bench_Trash_bin (16 x 16)"
            },
            {
                "url": "assets/Seasonal Tileset/5 - Misc. universal tiles/Snack_machine_Bench_Trash_bin (16 x 16).png",
                "type": "image",
                "key": "Snack_machine_Bench_Trash_bin (16 x 16)_1"
            },
            {
                "url": "assets/Seasonal Tilesets/1 - Grassland/Terrain (16 x 16).png",
                "frameConfig": {
                    "frameWidth": 32,
                    "frameHeight": 32,
                    "startFrame": 0,
                    "endFrame": -1,
                    "spacing": 0,
                    "margin": 0
                },
                "type": "spritesheet",
                "key": "Terrain (16 x 16)"
            },
            {
                "url": "assets/Seasonal Tilesets/2 - Autumn Forest/Terrain (16 x 16).png",
                "frameConfig": {
                    "frameWidth": 32,
                    "frameHeight": 32,
                    "startFrame": 0,
                    "endFrame": -1,
                    "spacing": 0,
                    "margin": 0
                },
                "type": "spritesheet",
                "key": "Terrain (16 x 16)_1"
            },
            {
                "url": "assets/Seasonal Tilesets/3 - Tropics/Terrain (16 x 16).png",
                "frameConfig": {
                    "frameWidth": 32,
                    "frameHeight": 32,
                    "startFrame": 0,
                    "endFrame": -1,
                    "spacing": 0,
                    "margin": 0
                },
                "type": "spritesheet",
                "key": "Terrain (16 x 16)_2"
            },
            {
                "url": "assets/Seasonal Tilesets/4 - Winter World/Terrain (16 x 16).png",
                "frameConfig": {
                    "frameWidth": 32,
                    "frameHeight": 32,
                    "startFrame": 0,
                    "endFrame": -1,
                    "spacing": 0,
                    "margin": 0
                },
                "type": "spritesheet",
                "key": "Terrain (16 x 16)_3"
            },
            {
                "url": "assets/Seasonal Tileset/1 - Grassland/Terrain (16 x 16).png",
                "type": "image",
                "key": "Terrain (16 x 16)_4"
            },
            {
                "url": "assets/Seasonal Tileset/2 - Autumn Forest/Terrain (16 x 16).png",
                "type": "image",
                "key": "Terrain (16 x 16)_5"
            },
            {
                "url": "assets/Seasonal Tileset/3 - Tropics/Terrain (16 x 16).png",
                "type": "image",
                "key": "Terrain (16 x 16)_6"
            },
            {
                "url": "assets/Seasonal Tileset/4 - Winter World/Terrain (16 x 16).png",
                "type": "image",
                "key": "Terrain (16 x 16)_7"
            },
            {
                "url": "assets/kenny art/Tiles/tile_0000.png",
                "type": "image",
                "key": "tile"
            },
            {
                "url": "assets/kenny platformer art/Tiles/tile_0000.png",
                "frameConfig": {
                    "frameWidth": 32,
                    "frameHeight": 32,
                    "startFrame": 0,
                    "endFrame": -1,
                    "spacing": 0,
                    "margin": 0
                },
                "type": "spritesheet",
                "key": "tile_0000"
            },
            {
                "url": "assets/kenny platformer art/Tiles/tile_0001.png",
                "frameConfig": {
                    "frameWidth": 32,
                    "frameHeight": 32,
                    "startFrame": 0,
                    "endFrame": -1,
                    "spacing": 0,
                    "margin": 0
                },
                "type": "spritesheet",
                "key": "tile_0001"
            },
            {
                "url": "assets/kenny platformer art/Tiles/tile_0002.png",
                "frameConfig": {
                    "frameWidth": 32,
                    "frameHeight": 32,
                    "startFrame": 0,
                    "endFrame": -1,
                    "spacing": 0,
                    "margin": 0
                },
                "type": "spritesheet",
                "key": "tile_0002"
            },
            {
                "url": "assets/kenny platformer art/Tiles/tile_0003.png",
                "frameConfig": {
                    "frameWidth": 32,
                    "frameHeight": 32,
                    "startFrame": 0,
                    "endFrame": -1,
                    "spacing": 0,
                    "margin": 0
                },
                "type": "spritesheet",
                "key": "tile_0003"
            },
            {
                "url": "assets/kenny platformer art/Tiles/tile_0004.png",
                "frameConfig": {
                    "frameWidth": 32,
                    "frameHeight": 32,
                    "startFrame": 0,
                    "endFrame": -1,
                    "spacing": 0,
                    "margin": 0
                },
                "type": "spritesheet",
                "key": "tile_0004"
            },
            {
                "url": "assets/kenny platformer art/Tiles/tile_0005.png",
                "frameConfig": {
                    "frameWidth": 32,
                    "frameHeight": 32,
                    "startFrame": 0,
                    "endFrame": -1,
                    "spacing": 0,
                    "margin": 0
                },
                "type": "spritesheet",
                "key": "tile_0005"
            },
            {
                "url": "assets/kenny platformer art/Tiles/tile_0006.png",
                "frameConfig": {
                    "frameWidth": 32,
                    "frameHeight": 32,
                    "startFrame": 0,
                    "endFrame": -1,
                    "spacing": 0,
                    "margin": 0
                },
                "type": "spritesheet",
                "key": "tile_0006"
            },
            {
                "url": "assets/kenny platformer art/Tiles/tile_0007.png",
                "frameConfig": {
                    "frameWidth": 32,
                    "frameHeight": 32,
                    "startFrame": 0,
                    "endFrame": -1,
                    "spacing": 0,
                    "margin": 0
                },
                "type": "spritesheet",
                "key": "tile_0007"
            },
            {
                "url": "assets/kenny platformer art/Tiles/tile_0008.png",
                "frameConfig": {
                    "frameWidth": 32,
                    "frameHeight": 32,
                    "startFrame": 0,
                    "endFrame": -1,
                    "spacing": 0,
                    "margin": 0
                },
                "type": "spritesheet",
                "key": "tile_0008"
            },
            {
                "url": "assets/kenny platformer art/Tiles/tile_0009.png",
                "frameConfig": {
                    "frameWidth": 32,
                    "frameHeight": 32,
                    "startFrame": 0,
                    "endFrame": -1,
                    "spacing": 0,
                    "margin": 0
                },
                "type": "spritesheet",
                "key": "tile_0009"
            },
            {
                "url": "assets/kenny platformer art/Tiles/tile_0010.png",
                "frameConfig": {
                    "frameWidth": 32,
                    "frameHeight": 32,
                    "startFrame": 0,
                    "endFrame": -1,
                    "spacing": 0,
                    "margin": 0
                },
                "type": "spritesheet",
                "key": "tile_0010"
            },
            {
                "url": "assets/kenny platformer art/Tiles/tile_0011.png",
                "frameConfig": {
                    "frameWidth": 32,
                    "frameHeight": 32,
                    "startFrame": 0,
                    "endFrame": -1,
                    "spacing": 0,
                    "margin": 0
                },
                "type": "spritesheet",
                "key": "tile_0011"
            },
            {
                "url": "assets/kenny platformer art/Tiles/tile_0012.png",
                "frameConfig": {
                    "frameWidth": 32,
                    "frameHeight": 32,
                    "startFrame": 0,
                    "endFrame": -1,
                    "spacing": 0,
                    "margin": 0
                },
                "type": "spritesheet",
                "key": "tile_0012"
            },
            {
                "url": "assets/kenny platformer art/Tiles/tile_0013.png",
                "frameConfig": {
                    "frameWidth": 32,
                    "frameHeight": 32,
                    "startFrame": 0,
                    "endFrame": -1,
                    "spacing": 0,
                    "margin": 0
                },
                "type": "spritesheet",
                "key": "tile_0013"
            },
            {
                "url": "assets/kenny platformer art/Tiles/tile_0014.png",
                "frameConfig": {
                    "frameWidth": 32,
                    "frameHeight": 32,
                    "startFrame": 0,
                    "endFrame": -1,
                    "spacing": 0,
                    "margin": 0
                },
                "type": "spritesheet",
                "key": "tile_0014"
            },
            {
                "url": "assets/kenny platformer art/Tiles/tile_0015.png",
                "frameConfig": {
                    "frameWidth": 32,
                    "frameHeight": 32,
                    "startFrame": 0,
                    "endFrame": -1,
                    "spacing": 0,
                    "margin": 0
                },
                "type": "spritesheet",
                "key": "tile_0015"
            },
            {
                "url": "assets/kenny platformer art/Tiles/tile_0016.png",
                "frameConfig": {
                    "frameWidth": 32,
                    "frameHeight": 32,
                    "startFrame": 0,
                    "endFrame": -1,
                    "spacing": 0,
                    "margin": 0
                },
                "type": "spritesheet",
                "key": "tile_0016"
            },
            {
                "url": "assets/kenny platformer art/Tiles/tile_0017.png",
                "frameConfig": {
                    "frameWidth": 32,
                    "frameHeight": 32,
                    "startFrame": 0,
                    "endFrame": -1,
                    "spacing": 0,
                    "margin": 0
                },
                "type": "spritesheet",
                "key": "tile_0017"
            },
            {
                "url": "assets/kenny platformer art/Tiles/tile_0018.png",
                "frameConfig": {
                    "frameWidth": 32,
                    "frameHeight": 32,
                    "startFrame": 0,
                    "endFrame": -1,
                    "spacing": 0,
                    "margin": 0
                },
                "type": "spritesheet",
                "key": "tile_0018"
            },
            {
                "url": "assets/kenny platformer art/Tiles/tile_0019.png",
                "frameConfig": {
                    "frameWidth": 32,
                    "frameHeight": 32,
                    "startFrame": 0,
                    "endFrame": -1,
                    "spacing": 0,
                    "margin": 0
                },
                "type": "spritesheet",
                "key": "tile_0019"
            },
            {
                "url": "assets/kenny platformer art/Tiles/tile_0020.png",
                "frameConfig": {
                    "frameWidth": 32,
                    "frameHeight": 32,
                    "startFrame": 0,
                    "endFrame": -1,
                    "spacing": 0,
                    "margin": 0
                },
                "type": "spritesheet",
                "key": "tile_0020"
            },
            {
                "url": "assets/kenny platformer art/Tiles/tile_0021.png",
                "frameConfig": {
                    "frameWidth": 32,
                    "frameHeight": 32,
                    "startFrame": 0,
                    "endFrame": -1,
                    "spacing": 0,
                    "margin": 0
                },
                "type": "spritesheet",
                "key": "tile_0021"
            },
            {
                "url": "assets/kenny platformer art/Tiles/tile_0022.png",
                "frameConfig": {
                    "frameWidth": 32,
                    "frameHeight": 32,
                    "startFrame": 0,
                    "endFrame": -1,
                    "spacing": 0,
                    "margin": 0
                },
                "type": "spritesheet",
                "key": "tile_0022"
            },
            {
                "url": "assets/kenny platformer art/Tiles/tile_0023.png",
                "frameConfig": {
                    "frameWidth": 32,
                    "frameHeight": 32,
                    "startFrame": 0,
                    "endFrame": -1,
                    "spacing": 0,
                    "margin": 0
                },
                "type": "spritesheet",
                "key": "tile_0023"
            },
            {
                "url": "assets/kenny platformer art/Tiles/tile_0024.png",
                "frameConfig": {
                    "frameWidth": 32,
                    "frameHeight": 32,
                    "startFrame": 0,
                    "endFrame": -1,
                    "spacing": 0,
                    "margin": 0
                },
                "type": "spritesheet",
                "key": "tile_0024"
            },
            {
                "url": "assets/kenny platformer art/Tiles/tile_0025.png",
                "frameConfig": {
                    "frameWidth": 32,
                    "frameHeight": 32,
                    "startFrame": 0,
                    "endFrame": -1,
                    "spacing": 0,
                    "margin": 0
                },
                "type": "spritesheet",
                "key": "tile_0025"
            },
            {
                "url": "assets/kenny platformer art/Tiles/tile_0026.png",
                "frameConfig": {
                    "frameWidth": 32,
                    "frameHeight": 32,
                    "startFrame": 0,
                    "endFrame": -1,
                    "spacing": 0,
                    "margin": 0
                },
                "type": "spritesheet",
                "key": "tile_0026"
            },
            {
                "url": "assets/kenny platformer art/Tiles/tile_0027.png",
                "frameConfig": {
                    "frameWidth": 32,
                    "frameHeight": 32,
                    "startFrame": 0,
                    "endFrame": -1,
                    "spacing": 0,
                    "margin": 0
                },
                "type": "spritesheet",
                "key": "tile_0027"
            },
            {
                "url": "assets/kenny platformer art/Tiles/tile_0028.png",
                "frameConfig": {
                    "frameWidth": 32,
                    "frameHeight": 32,
                    "startFrame": 0,
                    "endFrame": -1,
                    "spacing": 0,
                    "margin": 0
                },
                "type": "spritesheet",
                "key": "tile_0028"
            },
            {
                "url": "assets/kenny platformer art/Tiles/tile_0029.png",
                "frameConfig": {
                    "frameWidth": 32,
                    "frameHeight": 32,
                    "startFrame": 0,
                    "endFrame": -1,
                    "spacing": 0,
                    "margin": 0
                },
                "type": "spritesheet",
                "key": "tile_0029"
            },
            {
                "url": "assets/kenny platformer art/Tiles/tile_0030.png",
                "frameConfig": {
                    "frameWidth": 32,
                    "frameHeight": 32,
                    "startFrame": 0,
                    "endFrame": -1,
                    "spacing": 0,
                    "margin": 0
                },
                "type": "spritesheet",
                "key": "tile_0030"
            },
            {
                "url": "assets/kenny platformer art/Tiles/tile_0031.png",
                "frameConfig": {
                    "frameWidth": 32,
                    "frameHeight": 32,
                    "startFrame": 0,
                    "endFrame": -1,
                    "spacing": 0,
                    "margin": 0
                },
                "type": "spritesheet",
                "key": "tile_0031"
            },
            {
                "url": "assets/kenny platformer art/Tiles/tile_0032.png",
                "frameConfig": {
                    "frameWidth": 32,
                    "frameHeight": 32,
                    "startFrame": 0,
                    "endFrame": -1,
                    "spacing": 0,
                    "margin": 0
                },
                "type": "spritesheet",
                "key": "tile_0032"
            },
            {
                "url": "assets/kenny platformer art/Tiles/tile_0033.png",
                "frameConfig": {
                    "frameWidth": 32,
                    "frameHeight": 32,
                    "startFrame": 0,
                    "endFrame": -1,
                    "spacing": 0,
                    "margin": 0
                },
                "type": "spritesheet",
                "key": "tile_0033"
            },
            {
                "url": "assets/kenny platformer art/Tiles/tile_0034.png",
                "frameConfig": {
                    "frameWidth": 32,
                    "frameHeight": 32,
                    "startFrame": 0,
                    "endFrame": -1,
                    "spacing": 0,
                    "margin": 0
                },
                "type": "spritesheet",
                "key": "tile_0034"
            },
            {
                "url": "assets/kenny platformer art/Tiles/tile_0035.png",
                "frameConfig": {
                    "frameWidth": 32,
                    "frameHeight": 32,
                    "startFrame": 0,
                    "endFrame": -1,
                    "spacing": 0,
                    "margin": 0
                },
                "type": "spritesheet",
                "key": "tile_0035"
            },
            {
                "url": "assets/kenny platformer art/Tiles/tile_0036.png",
                "frameConfig": {
                    "frameWidth": 32,
                    "frameHeight": 32,
                    "startFrame": 0,
                    "endFrame": -1,
                    "spacing": 0,
                    "margin": 0
                },
                "type": "spritesheet",
                "key": "tile_0036"
            },
            {
                "url": "assets/kenny platformer art/Tiles/tile_0037.png",
                "frameConfig": {
                    "frameWidth": 32,
                    "frameHeight": 32,
                    "startFrame": 0,
                    "endFrame": -1,
                    "spacing": 0,
                    "margin": 0
                },
                "type": "spritesheet",
                "key": "tile_0037"
            },
            {
                "url": "assets/kenny platformer art/Tiles/tile_0038.png",
                "frameConfig": {
                    "frameWidth": 32,
                    "frameHeight": 32,
                    "startFrame": 0,
                    "endFrame": -1,
                    "spacing": 0,
                    "margin": 0
                },
                "type": "spritesheet",
                "key": "tile_0038"
            },
            {
                "url": "assets/kenny platformer art/Tiles/tile_0039.png",
                "frameConfig": {
                    "frameWidth": 32,
                    "frameHeight": 32,
                    "startFrame": 0,
                    "endFrame": -1,
                    "spacing": 0,
                    "margin": 0
                },
                "type": "spritesheet",
                "key": "tile_0039"
            },
            {
                "url": "assets/kenny platformer art/Tiles/tile_0040.png",
                "frameConfig": {
                    "frameWidth": 32,
                    "frameHeight": 32,
                    "startFrame": 0,
                    "endFrame": -1,
                    "spacing": 0,
                    "margin": 0
                },
                "type": "spritesheet",
                "key": "tile_0040"
            },
            {
                "url": "assets/kenny platformer art/Tiles/tile_0041.png",
                "frameConfig": {
                    "frameWidth": 32,
                    "frameHeight": 32,
                    "startFrame": 0,
                    "endFrame": -1,
                    "spacing": 0,
                    "margin": 0
                },
                "type": "spritesheet",
                "key": "tile_0041"
            },
            {
                "url": "assets/kenny platformer art/Tiles/tile_0042.png",
                "frameConfig": {
                    "frameWidth": 32,
                    "frameHeight": 32,
                    "startFrame": 0,
                    "endFrame": -1,
                    "spacing": 0,
                    "margin": 0
                },
                "type": "spritesheet",
                "key": "tile_0042"
            },
            {
                "url": "assets/kenny platformer art/Tiles/tile_0043.png",
                "frameConfig": {
                    "frameWidth": 32,
                    "frameHeight": 32,
                    "startFrame": 0,
                    "endFrame": -1,
                    "spacing": 0,
                    "margin": 0
                },
                "type": "spritesheet",
                "key": "tile_0043"
            },
            {
                "url": "assets/kenny platformer art/Tiles/tile_0044.png",
                "frameConfig": {
                    "frameWidth": 32,
                    "frameHeight": 32,
                    "startFrame": 0,
                    "endFrame": -1,
                    "spacing": 0,
                    "margin": 0
                },
                "type": "spritesheet",
                "key": "tile_0044"
            },
            {
                "url": "assets/kenny platformer art/Tiles/tile_0045.png",
                "frameConfig": {
                    "frameWidth": 32,
                    "frameHeight": 32,
                    "startFrame": 0,
                    "endFrame": -1,
                    "spacing": 0,
                    "margin": 0
                },
                "type": "spritesheet",
                "key": "tile_0045"
            },
            {
                "url": "assets/kenny platformer art/Tiles/tile_0046.png",
                "frameConfig": {
                    "frameWidth": 32,
                    "frameHeight": 32,
                    "startFrame": 0,
                    "endFrame": -1,
                    "spacing": 0,
                    "margin": 0
                },
                "type": "spritesheet",
                "key": "tile_0046"
            },
            {
                "url": "assets/kenny platformer art/Tiles/tile_0047.png",
                "frameConfig": {
                    "frameWidth": 32,
                    "frameHeight": 32,
                    "startFrame": 0,
                    "endFrame": -1,
                    "spacing": 0,
                    "margin": 0
                },
                "type": "spritesheet",
                "key": "tile_0047"
            },
            {
                "url": "assets/kenny platformer art/Tiles/tile_0048.png",
                "frameConfig": {
                    "frameWidth": 32,
                    "frameHeight": 32,
                    "startFrame": 0,
                    "endFrame": -1,
                    "spacing": 0,
                    "margin": 0
                },
                "type": "spritesheet",
                "key": "tile_0048"
            },
            {
                "url": "assets/kenny platformer art/Tiles/tile_0049.png",
                "frameConfig": {
                    "frameWidth": 32,
                    "frameHeight": 32,
                    "startFrame": 0,
                    "endFrame": -1,
                    "spacing": 0,
                    "margin": 0
                },
                "type": "spritesheet",
                "key": "tile_0049"
            },
            {
                "url": "assets/kenny platformer art/Tiles/tile_0050.png",
                "frameConfig": {
                    "frameWidth": 32,
                    "frameHeight": 32,
                    "startFrame": 0,
                    "endFrame": -1,
                    "spacing": 0,
                    "margin": 0
                },
                "type": "spritesheet",
                "key": "tile_0050"
            },
            {
                "url": "assets/kenny platformer art/Tiles/tile_0051.png",
                "frameConfig": {
                    "frameWidth": 32,
                    "frameHeight": 32,
                    "startFrame": 0,
                    "endFrame": -1,
                    "spacing": 0,
                    "margin": 0
                },
                "type": "spritesheet",
                "key": "tile_0051"
            },
            {
                "url": "assets/kenny platformer art/Tiles/tile_0052.png",
                "frameConfig": {
                    "frameWidth": 32,
                    "frameHeight": 32,
                    "startFrame": 0,
                    "endFrame": -1,
                    "spacing": 0,
                    "margin": 0
                },
                "type": "spritesheet",
                "key": "tile_0052"
            },
            {
                "url": "assets/kenny platformer art/Tiles/tile_0053.png",
                "frameConfig": {
                    "frameWidth": 32,
                    "frameHeight": 32,
                    "startFrame": 0,
                    "endFrame": -1,
                    "spacing": 0,
                    "margin": 0
                },
                "type": "spritesheet",
                "key": "tile_0053"
            },
            {
                "url": "assets/kenny platformer art/Tiles/tile_0054.png",
                "frameConfig": {
                    "frameWidth": 32,
                    "frameHeight": 32,
                    "startFrame": 0,
                    "endFrame": -1,
                    "spacing": 0,
                    "margin": 0
                },
                "type": "spritesheet",
                "key": "tile_0054"
            },
            {
                "url": "assets/kenny platformer art/Tiles/tile_0055.png",
                "frameConfig": {
                    "frameWidth": 32,
                    "frameHeight": 32,
                    "startFrame": 0,
                    "endFrame": -1,
                    "spacing": 0,
                    "margin": 0
                },
                "type": "spritesheet",
                "key": "tile_0055"
            },
            {
                "url": "assets/kenny platformer art/Tiles/tile_0056.png",
                "frameConfig": {
                    "frameWidth": 32,
                    "frameHeight": 32,
                    "startFrame": 0,
                    "endFrame": -1,
                    "spacing": 0,
                    "margin": 0
                },
                "type": "spritesheet",
                "key": "tile_0056"
            },
            {
                "url": "assets/kenny platformer art/Tiles/tile_0057.png",
                "frameConfig": {
                    "frameWidth": 32,
                    "frameHeight": 32,
                    "startFrame": 0,
                    "endFrame": -1,
                    "spacing": 0,
                    "margin": 0
                },
                "type": "spritesheet",
                "key": "tile_0057"
            },
            {
                "url": "assets/kenny platformer art/Tiles/tile_0058.png",
                "frameConfig": {
                    "frameWidth": 32,
                    "frameHeight": 32,
                    "startFrame": 0,
                    "endFrame": -1,
                    "spacing": 0,
                    "margin": 0
                },
                "type": "spritesheet",
                "key": "tile_0058"
            },
            {
                "url": "assets/kenny platformer art/Tiles/tile_0059.png",
                "frameConfig": {
                    "frameWidth": 32,
                    "frameHeight": 32,
                    "startFrame": 0,
                    "endFrame": -1,
                    "spacing": 0,
                    "margin": 0
                },
                "type": "spritesheet",
                "key": "tile_0059"
            },
            {
                "url": "assets/kenny platformer art/Tiles/tile_0060.png",
                "frameConfig": {
                    "frameWidth": 32,
                    "frameHeight": 32,
                    "startFrame": 0,
                    "endFrame": -1,
                    "spacing": 0,
                    "margin": 0
                },
                "type": "spritesheet",
                "key": "tile_0060"
            },
            {
                "url": "assets/kenny platformer art/Tiles/tile_0061.png",
                "frameConfig": {
                    "frameWidth": 32,
                    "frameHeight": 32,
                    "startFrame": 0,
                    "endFrame": -1,
                    "spacing": 0,
                    "margin": 0
                },
                "type": "spritesheet",
                "key": "tile_0061"
            },
            {
                "url": "assets/kenny platformer art/Tiles/tile_0062.png",
                "frameConfig": {
                    "frameWidth": 32,
                    "frameHeight": 32,
                    "startFrame": 0,
                    "endFrame": -1,
                    "spacing": 0,
                    "margin": 0
                },
                "type": "spritesheet",
                "key": "tile_0062"
            },
            {
                "url": "assets/kenny platformer art/Tiles/tile_0063.png",
                "frameConfig": {
                    "frameWidth": 32,
                    "frameHeight": 32,
                    "startFrame": 0,
                    "endFrame": -1,
                    "spacing": 0,
                    "margin": 0
                },
                "type": "spritesheet",
                "key": "tile_0063"
            },
            {
                "url": "assets/kenny platformer art/Tiles/tile_0064.png",
                "frameConfig": {
                    "frameWidth": 32,
                    "frameHeight": 32,
                    "startFrame": 0,
                    "endFrame": -1,
                    "spacing": 0,
                    "margin": 0
                },
                "type": "spritesheet",
                "key": "tile_0064"
            },
            {
                "url": "assets/kenny platformer art/Tiles/tile_0065.png",
                "frameConfig": {
                    "frameWidth": 32,
                    "frameHeight": 32,
                    "startFrame": 0,
                    "endFrame": -1,
                    "spacing": 0,
                    "margin": 0
                },
                "type": "spritesheet",
                "key": "tile_0065"
            },
            {
                "url": "assets/kenny platformer art/Tiles/tile_0066.png",
                "frameConfig": {
                    "frameWidth": 32,
                    "frameHeight": 32,
                    "startFrame": 0,
                    "endFrame": -1,
                    "spacing": 0,
                    "margin": 0
                },
                "type": "spritesheet",
                "key": "tile_0066"
            },
            {
                "url": "assets/kenny platformer art/Tiles/tile_0067.png",
                "frameConfig": {
                    "frameWidth": 32,
                    "frameHeight": 32,
                    "startFrame": 0,
                    "endFrame": -1,
                    "spacing": 0,
                    "margin": 0
                },
                "type": "spritesheet",
                "key": "tile_0067"
            },
            {
                "url": "assets/kenny platformer art/Tiles/tile_0068.png",
                "frameConfig": {
                    "frameWidth": 32,
                    "frameHeight": 32,
                    "startFrame": 0,
                    "endFrame": -1,
                    "spacing": 0,
                    "margin": 0
                },
                "type": "spritesheet",
                "key": "tile_0068"
            },
            {
                "url": "assets/kenny platformer art/Tiles/tile_0069.png",
                "frameConfig": {
                    "frameWidth": 32,
                    "frameHeight": 32,
                    "startFrame": 0,
                    "endFrame": -1,
                    "spacing": 0,
                    "margin": 0
                },
                "type": "spritesheet",
                "key": "tile_0069"
            },
            {
                "url": "assets/kenny platformer art/Tiles/tile_0070.png",
                "frameConfig": {
                    "frameWidth": 32,
                    "frameHeight": 32,
                    "startFrame": 0,
                    "endFrame": -1,
                    "spacing": 0,
                    "margin": 0
                },
                "type": "spritesheet",
                "key": "tile_0070"
            },
            {
                "url": "assets/kenny platformer art/Tiles/tile_0071.png",
                "frameConfig": {
                    "frameWidth": 32,
                    "frameHeight": 32,
                    "startFrame": 0,
                    "endFrame": -1,
                    "spacing": 0,
                    "margin": 0
                },
                "type": "spritesheet",
                "key": "tile_0071"
            },
            {
                "url": "assets/kenny platformer art/Tiles/tile_0072.png",
                "frameConfig": {
                    "frameWidth": 32,
                    "frameHeight": 32,
                    "startFrame": 0,
                    "endFrame": -1,
                    "spacing": 0,
                    "margin": 0
                },
                "type": "spritesheet",
                "key": "tile_0072"
            },
            {
                "url": "assets/kenny platformer art/Tiles/tile_0073.png",
                "frameConfig": {
                    "frameWidth": 32,
                    "frameHeight": 32,
                    "startFrame": 0,
                    "endFrame": -1,
                    "spacing": 0,
                    "margin": 0
                },
                "type": "spritesheet",
                "key": "tile_0073"
            },
            {
                "url": "assets/kenny platformer art/Tiles/tile_0074.png",
                "frameConfig": {
                    "frameWidth": 32,
                    "frameHeight": 32,
                    "startFrame": 0,
                    "endFrame": -1,
                    "spacing": 0,
                    "margin": 0
                },
                "type": "spritesheet",
                "key": "tile_0074"
            },
            {
                "url": "assets/kenny platformer art/Tiles/tile_0075.png",
                "frameConfig": {
                    "frameWidth": 32,
                    "frameHeight": 32,
                    "startFrame": 0,
                    "endFrame": -1,
                    "spacing": 0,
                    "margin": 0
                },
                "type": "spritesheet",
                "key": "tile_0075"
            },
            {
                "url": "assets/kenny platformer art/Tiles/tile_0076.png",
                "frameConfig": {
                    "frameWidth": 32,
                    "frameHeight": 32,
                    "startFrame": 0,
                    "endFrame": -1,
                    "spacing": 0,
                    "margin": 0
                },
                "type": "spritesheet",
                "key": "tile_0076"
            },
            {
                "url": "assets/kenny platformer art/Tiles/tile_0077.png",
                "frameConfig": {
                    "frameWidth": 32,
                    "frameHeight": 32,
                    "startFrame": 0,
                    "endFrame": -1,
                    "spacing": 0,
                    "margin": 0
                },
                "type": "spritesheet",
                "key": "tile_0077"
            },
            {
                "url": "assets/kenny platformer art/Tiles/tile_0078.png",
                "frameConfig": {
                    "frameWidth": 32,
                    "frameHeight": 32,
                    "startFrame": 0,
                    "endFrame": -1,
                    "spacing": 0,
                    "margin": 0
                },
                "type": "spritesheet",
                "key": "tile_0078"
            },
            {
                "url": "assets/kenny platformer art/Tiles/tile_0079.png",
                "frameConfig": {
                    "frameWidth": 32,
                    "frameHeight": 32,
                    "startFrame": 0,
                    "endFrame": -1,
                    "spacing": 0,
                    "margin": 0
                },
                "type": "spritesheet",
                "key": "tile_0079"
            },
            {
                "url": "assets/kenny platformer art/Tiles/tile_0080.png",
                "frameConfig": {
                    "frameWidth": 32,
                    "frameHeight": 32,
                    "startFrame": 0,
                    "endFrame": -1,
                    "spacing": 0,
                    "margin": 0
                },
                "type": "spritesheet",
                "key": "tile_0080"
            },
            {
                "url": "assets/kenny platformer art/Tiles/tile_0081.png",
                "frameConfig": {
                    "frameWidth": 32,
                    "frameHeight": 32,
                    "startFrame": 0,
                    "endFrame": -1,
                    "spacing": 0,
                    "margin": 0
                },
                "type": "spritesheet",
                "key": "tile_0081"
            },
            {
                "url": "assets/kenny platformer art/Tiles/tile_0082.png",
                "frameConfig": {
                    "frameWidth": 32,
                    "frameHeight": 32,
                    "startFrame": 0,
                    "endFrame": -1,
                    "spacing": 0,
                    "margin": 0
                },
                "type": "spritesheet",
                "key": "tile_0082"
            },
            {
                "url": "assets/kenny platformer art/Tiles/tile_0083.png",
                "frameConfig": {
                    "frameWidth": 32,
                    "frameHeight": 32,
                    "startFrame": 0,
                    "endFrame": -1,
                    "spacing": 0,
                    "margin": 0
                },
                "type": "spritesheet",
                "key": "tile_0083"
            },
            {
                "url": "assets/kenny platformer art/Tiles/tile_0084.png",
                "frameConfig": {
                    "frameWidth": 32,
                    "frameHeight": 32,
                    "startFrame": 0,
                    "endFrame": -1,
                    "spacing": 0,
                    "margin": 0
                },
                "type": "spritesheet",
                "key": "tile_0084"
            },
            {
                "url": "assets/kenny platformer art/Tiles/tile_0085.png",
                "frameConfig": {
                    "frameWidth": 32,
                    "frameHeight": 32,
                    "startFrame": 0,
                    "endFrame": -1,
                    "spacing": 0,
                    "margin": 0
                },
                "type": "spritesheet",
                "key": "tile_0085"
            },
            {
                "url": "assets/kenny platformer art/Tiles/tile_0086.png",
                "frameConfig": {
                    "frameWidth": 32,
                    "frameHeight": 32,
                    "startFrame": 0,
                    "endFrame": -1,
                    "spacing": 0,
                    "margin": 0
                },
                "type": "spritesheet",
                "key": "tile_0086"
            },
            {
                "url": "assets/kenny platformer art/Tiles/tile_0087.png",
                "frameConfig": {
                    "frameWidth": 32,
                    "frameHeight": 32,
                    "startFrame": 0,
                    "endFrame": -1,
                    "spacing": 0,
                    "margin": 0
                },
                "type": "spritesheet",
                "key": "tile_0087"
            },
            {
                "url": "assets/kenny platformer art/Tiles/tile_0088.png",
                "frameConfig": {
                    "frameWidth": 32,
                    "frameHeight": 32,
                    "startFrame": 0,
                    "endFrame": -1,
                    "spacing": 0,
                    "margin": 0
                },
                "type": "spritesheet",
                "key": "tile_0088"
            },
            {
                "url": "assets/kenny platformer art/Tiles/tile_0089.png",
                "frameConfig": {
                    "frameWidth": 32,
                    "frameHeight": 32,
                    "startFrame": 0,
                    "endFrame": -1,
                    "spacing": 0,
                    "margin": 0
                },
                "type": "spritesheet",
                "key": "tile_0089"
            },
            {
                "url": "assets/kenny platformer art/Tiles/tile_0090.png",
                "frameConfig": {
                    "frameWidth": 32,
                    "frameHeight": 32,
                    "startFrame": 0,
                    "endFrame": -1,
                    "spacing": 0,
                    "margin": 0
                },
                "type": "spritesheet",
                "key": "tile_0090"
            },
            {
                "url": "assets/kenny platformer art/Tiles/tile_0091.png",
                "frameConfig": {
                    "frameWidth": 32,
                    "frameHeight": 32,
                    "startFrame": 0,
                    "endFrame": -1,
                    "spacing": 0,
                    "margin": 0
                },
                "type": "spritesheet",
                "key": "tile_0091"
            },
            {
                "url": "assets/kenny platformer art/Tiles/tile_0092.png",
                "frameConfig": {
                    "frameWidth": 32,
                    "frameHeight": 32,
                    "startFrame": 0,
                    "endFrame": -1,
                    "spacing": 0,
                    "margin": 0
                },
                "type": "spritesheet",
                "key": "tile_0092"
            },
            {
                "url": "assets/kenny platformer art/Tiles/tile_0093.png",
                "frameConfig": {
                    "frameWidth": 32,
                    "frameHeight": 32,
                    "startFrame": 0,
                    "endFrame": -1,
                    "spacing": 0,
                    "margin": 0
                },
                "type": "spritesheet",
                "key": "tile_0093"
            },
            {
                "url": "assets/kenny platformer art/Tiles/tile_0094.png",
                "frameConfig": {
                    "frameWidth": 32,
                    "frameHeight": 32,
                    "startFrame": 0,
                    "endFrame": -1,
                    "spacing": 0,
                    "margin": 0
                },
                "type": "spritesheet",
                "key": "tile_0094"
            },
            {
                "url": "assets/kenny platformer art/Tiles/tile_0095.png",
                "frameConfig": {
                    "frameWidth": 32,
                    "frameHeight": 32,
                    "startFrame": 0,
                    "endFrame": -1,
                    "spacing": 0,
                    "margin": 0
                },
                "type": "spritesheet",
                "key": "tile_0095"
            },
            {
                "url": "assets/kenny platformer art/Tiles/tile_0096.png",
                "frameConfig": {
                    "frameWidth": 32,
                    "frameHeight": 32,
                    "startFrame": 0,
                    "endFrame": -1,
                    "spacing": 0,
                    "margin": 0
                },
                "type": "spritesheet",
                "key": "tile_0096"
            },
            {
                "url": "assets/kenny platformer art/Tiles/tile_0097.png",
                "frameConfig": {
                    "frameWidth": 32,
                    "frameHeight": 32,
                    "startFrame": 0,
                    "endFrame": -1,
                    "spacing": 0,
                    "margin": 0
                },
                "type": "spritesheet",
                "key": "tile_0097"
            },
            {
                "url": "assets/kenny platformer art/Tiles/tile_0098.png",
                "frameConfig": {
                    "frameWidth": 32,
                    "frameHeight": 32,
                    "startFrame": 0,
                    "endFrame": -1,
                    "spacing": 0,
                    "margin": 0
                },
                "type": "spritesheet",
                "key": "tile_0098"
            },
            {
                "url": "assets/kenny platformer art/Tiles/tile_0099.png",
                "frameConfig": {
                    "frameWidth": 32,
                    "frameHeight": 32,
                    "startFrame": 0,
                    "endFrame": -1,
                    "spacing": 0,
                    "margin": 0
                },
                "type": "spritesheet",
                "key": "tile_0099"
            },
            {
                "url": "assets/kenny art/Tiles/tile_0001.png",
                "type": "image",
                "key": "tile_1"
            },
            {
                "url": "assets/kenny art/Tiles/tile_0010.png",
                "type": "image",
                "key": "tile_10"
            },
            {
                "url": "assets/kenny art/Tiles/tile_0011.png",
                "type": "image",
                "key": "tile_11"
            },
            {
                "url": "assets/kenny art/Tiles/tile_0012.png",
                "type": "image",
                "key": "tile_12"
            },
            {
                "url": "assets/kenny art/Tiles/tile_0013.png",
                "type": "image",
                "key": "tile_13"
            },
            {
                "url": "assets/kenny art/Tiles/tile_0014.png",
                "type": "image",
                "key": "tile_14"
            },
            {
                "url": "assets/kenny art/Tiles/tile_0015.png",
                "type": "image",
                "key": "tile_15"
            },
            {
                "url": "assets/kenny art/Tiles/tile_0016.png",
                "type": "image",
                "key": "tile_16"
            },
            {
                "url": "assets/kenny art/Tiles/tile_0017.png",
                "type": "image",
                "key": "tile_17"
            },
            {
                "url": "assets/kenny art/Tiles/tile_0018.png",
                "type": "image",
                "key": "tile_18"
            },
            {
                "url": "assets/kenny art/Tiles/tile_0019.png",
                "type": "image",
                "key": "tile_19"
            },
            {
                "url": "assets/kenny art/Tiles/tile_0002.png",
                "type": "image",
                "key": "tile_2"
            },
            {
                "url": "assets/kenny art/Tiles/tile_0020.png",
                "type": "image",
                "key": "tile_20"
            },
            {
                "url": "assets/kenny art/Tiles/tile_0021.png",
                "type": "image",
                "key": "tile_21"
            },
            {
                "url": "assets/kenny art/Tiles/tile_0022.png",
                "type": "image",
                "key": "tile_22"
            },
            {
                "url": "assets/kenny art/Tiles/tile_0023.png",
                "type": "image",
                "key": "tile_23"
            },
            {
                "url": "assets/kenny art/Tiles/tile_0024.png",
                "type": "image",
                "key": "tile_24"
            },
            {
                "url": "assets/kenny art/Tiles/tile_0025.png",
                "type": "image",
                "key": "tile_25"
            },
            {
                "url": "assets/kenny art/Tiles/tile_0026.png",
                "type": "image",
                "key": "tile_26"
            },
            {
                "url": "assets/kenny art/Tiles/tile_0027.png",
                "type": "image",
                "key": "tile_27"
            },
            {
                "url": "assets/kenny art/Tiles/tile_0028.png",
                "type": "image",
                "key": "tile_28"
            },
            {
                "url": "assets/kenny art/Tiles/tile_0029.png",
                "type": "image",
                "key": "tile_29"
            },
            {
                "url": "assets/kenny art/Tiles/tile_0003.png",
                "type": "image",
                "key": "tile_3"
            },
            {
                "url": "assets/kenny art/Tiles/tile_0030.png",
                "type": "image",
                "key": "tile_30"
            },
            {
                "url": "assets/kenny art/Tiles/tile_0031.png",
                "type": "image",
                "key": "tile_31"
            },
            {
                "url": "assets/kenny art/Tiles/tile_0032.png",
                "type": "image",
                "key": "tile_32"
            },
            {
                "url": "assets/kenny art/Tiles/tile_0033.png",
                "type": "image",
                "key": "tile_33"
            },
            {
                "url": "assets/kenny art/Tiles/tile_0034.png",
                "type": "image",
                "key": "tile_34"
            },
            {
                "url": "assets/kenny art/Tiles/tile_0035.png",
                "type": "image",
                "key": "tile_35"
            },
            {
                "url": "assets/kenny art/Tiles/tile_0036.png",
                "type": "image",
                "key": "tile_36"
            },
            {
                "url": "assets/kenny art/Tiles/tile_0037.png",
                "type": "image",
                "key": "tile_37"
            },
            {
                "url": "assets/kenny art/Tiles/tile_0038.png",
                "type": "image",
                "key": "tile_38"
            },
            {
                "url": "assets/kenny art/Tiles/tile_0039.png",
                "type": "image",
                "key": "tile_39"
            },
            {
                "url": "assets/kenny art/Tiles/tile_0004.png",
                "type": "image",
                "key": "tile_4"
            },
            {
                "url": "assets/kenny art/Tiles/tile_0040.png",
                "type": "image",
                "key": "tile_40"
            },
            {
                "url": "assets/kenny art/Tiles/tile_0041.png",
                "type": "image",
                "key": "tile_41"
            },
            {
                "url": "assets/kenny art/Tiles/tile_0042.png",
                "type": "image",
                "key": "tile_42"
            },
            {
                "url": "assets/kenny art/Tiles/tile_0043.png",
                "type": "image",
                "key": "tile_43"
            },
            {
                "url": "assets/kenny art/Tiles/tile_0044.png",
                "type": "image",
                "key": "tile_44"
            },
            {
                "url": "assets/kenny art/Tiles/tile_0045.png",
                "type": "image",
                "key": "tile_45"
            },
            {
                "url": "assets/kenny art/Tiles/tile_0046.png",
                "type": "image",
                "key": "tile_46"
            },
            {
                "url": "assets/kenny art/Tiles/tile_0047.png",
                "type": "image",
                "key": "tile_47"
            },
            {
                "url": "assets/kenny art/Tiles/tile_0048.png",
                "type": "image",
                "key": "tile_48"
            },
            {
                "url": "assets/kenny art/Tiles/tile_0049.png",
                "type": "image",
                "key": "tile_49"
            },
            {
                "url": "assets/kenny art/Tiles/tile_0005.png",
                "type": "image",
                "key": "tile_5"
            },
            {
                "url": "assets/kenny art/Tiles/tile_0050.png",
                "type": "image",
                "key": "tile_50"
            },
            {
                "url": "assets/kenny art/Tiles/tile_0051.png",
                "type": "image",
                "key": "tile_51"
            },
            {
                "url": "assets/kenny art/Tiles/tile_0052.png",
                "type": "image",
                "key": "tile_52"
            },
            {
                "url": "assets/kenny art/Tiles/tile_0053.png",
                "type": "image",
                "key": "tile_53"
            },
            {
                "url": "assets/kenny art/Tiles/tile_0054.png",
                "type": "image",
                "key": "tile_54"
            },
            {
                "url": "assets/kenny art/Tiles/tile_0055.png",
                "type": "image",
                "key": "tile_55"
            },
            {
                "url": "assets/kenny art/Tiles/tile_0056.png",
                "type": "image",
                "key": "tile_56"
            },
            {
                "url": "assets/kenny art/Tiles/tile_0057.png",
                "type": "image",
                "key": "tile_57"
            },
            {
                "url": "assets/kenny art/Tiles/tile_0058.png",
                "type": "image",
                "key": "tile_58"
            },
            {
                "url": "assets/kenny art/Tiles/tile_0059.png",
                "type": "image",
                "key": "tile_59"
            },
            {
                "url": "assets/kenny art/Tiles/tile_0006.png",
                "type": "image",
                "key": "tile_6"
            },
            {
                "url": "assets/kenny art/Tiles/tile_0060.png",
                "type": "image",
                "key": "tile_60"
            },
            {
                "url": "assets/kenny art/Tiles/tile_0061.png",
                "type": "image",
                "key": "tile_61"
            },
            {
                "url": "assets/kenny art/Tiles/tile_0062.png",
                "type": "image",
                "key": "tile_62"
            },
            {
                "url": "assets/kenny art/Tiles/tile_0063.png",
                "type": "image",
                "key": "tile_63"
            },
            {
                "url": "assets/kenny art/Tiles/tile_0064.png",
                "type": "image",
                "key": "tile_64"
            },
            {
                "url": "assets/kenny art/Tiles/tile_0065.png",
                "type": "image",
                "key": "tile_65"
            },
            {
                "url": "assets/kenny art/Tiles/tile_0066.png",
                "type": "image",
                "key": "tile_66"
            },
            {
                "url": "assets/kenny art/Tiles/tile_0067.png",
                "type": "image",
                "key": "tile_67"
            },
            {
                "url": "assets/kenny art/Tiles/tile_0068.png",
                "type": "image",
                "key": "tile_68"
            },
            {
                "url": "assets/kenny art/Tiles/tile_0069.png",
                "type": "image",
                "key": "tile_69"
            },
            {
                "url": "assets/kenny art/Tiles/tile_0007.png",
                "type": "image",
                "key": "tile_7"
            },
            {
                "url": "assets/kenny art/Tiles/tile_0070.png",
                "type": "image",
                "key": "tile_70"
            },
            {
                "url": "assets/kenny art/Tiles/tile_0071.png",
                "type": "image",
                "key": "tile_71"
            },
            {
                "url": "assets/kenny art/Tiles/tile_0072.png",
                "type": "image",
                "key": "tile_72"
            },
            {
                "url": "assets/kenny art/Tiles/tile_0073.png",
                "type": "image",
                "key": "tile_73"
            },
            {
                "url": "assets/kenny art/Tiles/tile_0074.png",
                "type": "image",
                "key": "tile_74"
            },
            {
                "url": "assets/kenny art/Tiles/tile_0075.png",
                "type": "image",
                "key": "tile_75"
            },
            {
                "url": "assets/kenny art/Tiles/tile_0076.png",
                "type": "image",
                "key": "tile_76"
            },
            {
                "url": "assets/kenny art/Tiles/tile_0077.png",
                "type": "image",
                "key": "tile_77"
            },
            {
                "url": "assets/kenny art/Tiles/tile_0078.png",
                "type": "image",
                "key": "tile_78"
            },
            {
                "url": "assets/kenny art/Tiles/tile_0079.png",
                "type": "image",
                "key": "tile_79"
            },
            {
                "url": "assets/kenny art/Tiles/tile_0008.png",
                "type": "image",
                "key": "tile_8"
            },
            {
                "url": "assets/kenny art/Tiles/tile_0080.png",
                "type": "image",
                "key": "tile_80"
            },
            {
                "url": "assets/kenny art/Tiles/tile_0081.png",
                "type": "image",
                "key": "tile_81"
            },
            {
                "url": "assets/kenny art/Tiles/tile_0082.png",
                "type": "image",
                "key": "tile_82"
            },
            {
                "url": "assets/kenny art/Tiles/tile_0083.png",
                "type": "image",
                "key": "tile_83"
            },
            {
                "url": "assets/kenny art/Tiles/tile_0084.png",
                "type": "image",
                "key": "tile_84"
            },
            {
                "url": "assets/kenny art/Tiles/tile_0085.png",
                "type": "image",
                "key": "tile_85"
            },
            {
                "url": "assets/kenny art/Tiles/tile_0086.png",
                "type": "image",
                "key": "tile_86"
            },
            {
                "url": "assets/kenny art/Tiles/tile_0087.png",
                "type": "image",
                "key": "tile_87"
            },
            {
                "url": "assets/kenny art/Tiles/tile_0088.png",
                "type": "image",
                "key": "tile_88"
            },
            {
                "url": "assets/kenny art/Tiles/tile_0089.png",
                "type": "image",
                "key": "tile_89"
            },
            {
                "url": "assets/kenny art/Tiles/tile_0009.png",
                "type": "image",
                "key": "tile_9"
            },
            {
                "url": "assets/kenny art/Tiles/tile_0090.png",
                "type": "image",
                "key": "tile_90"
            },
            {
                "url": "assets/kenny art/Tiles/tile_0091.png",
                "type": "image",
                "key": "tile_91"
            },
            {
                "url": "assets/kenny art/Tiles/tile_0092.png",
                "type": "image",
                "key": "tile_92"
            },
            {
                "url": "assets/kenny art/Tiles/tile_0093.png",
                "type": "image",
                "key": "tile_93"
            },
            {
                "url": "assets/kenny art/Tiles/tile_0094.png",
                "type": "image",
                "key": "tile_94"
            },
            {
                "url": "assets/kenny art/Tiles/tile_0095.png",
                "type": "image",
                "key": "tile_95"
            },
            {
                "url": "assets/kenny art/Tiles/tile_0096.png",
                "type": "image",
                "key": "tile_96"
            },
            {
                "url": "assets/kenny art/Tiles/tile_0097.png",
                "type": "image",
                "key": "tile_97"
            },
            {
                "url": "assets/kenny art/Tiles/tile_0098.png",
                "type": "image",
                "key": "tile_98"
            },
            {
                "url": "assets/kenny art/Tiles/tile_0099.png",
                "type": "image",
                "key": "tile_99"
            },
            {
                "url": "assets/kenny platformer art/Tilemap/tilemap.png",
                "frameConfig": {
                    "frameWidth": 32,
                    "frameHeight": 32,
                    "startFrame": 0,
                    "endFrame": -1,
                    "spacing": 0,
                    "margin": 0
                },
                "type": "spritesheet",
                "key": "tilemap"
            },
            {
                "url": "assets/kenny art/Tilemap/tilemap.png",
                "type": "image",
                "key": "tilemap_1"
            },
            {
                "url": "assets/kenny platformer art/Tilemap/tilemap_packed.png",
                "frameConfig": {
                    "frameWidth": 32,
                    "frameHeight": 32,
                    "startFrame": 0,
                    "endFrame": -1,
                    "spacing": 0,
                    "margin": 0
                },
                "type": "spritesheet",
                "key": "tilemap_packed"
            },
            {
                "url": "assets/kenny art/Tilemap/tilemap_packed.png",
                "type": "image",
                "key": "tilemap_packed_1"
            },
            {
                "url": "assets/Seasonal Tilesets/3 - Tropics/Tropics_entities (16 x 16).png",
                "frameConfig": {
                    "frameWidth": 32,
                    "frameHeight": 32,
                    "startFrame": 0,
                    "endFrame": -1,
                    "spacing": 0,
                    "margin": 0
                },
                "type": "spritesheet",
                "key": "Tropics_entities (16 x 16)"
            },
            {
                "url": "assets/Seasonal Tileset/3 - Tropics/Tropics_entities (16 x 16).png",
                "type": "image",
                "key": "Tropics_entities (16 x 16)_1"
            },
            {
                "url": "assets/Seasonal Tilesets/5 - Misc. universal tiles/Water_frames (16 x 32).png",
                "frameConfig": {
                    "frameWidth": 32,
                    "frameHeight": 32,
                    "startFrame": 0,
                    "endFrame": -1,
                    "spacing": 0,
                    "margin": 0
                },
                "type": "spritesheet",
                "key": "Water_frames (16 x 32)"
            },
            {
                "url": "assets/Seasonal Tileset/5 - Misc. universal tiles/Water_frames (16 x 32).png",
                "type": "image",
                "key": "Water_frames (16 x 32)_1"
            },
            {
                "url": "assets/Seasonal Tilesets/4 - Winter World/Winter_entities (16 x 16).png",
                "frameConfig": {
                    "frameWidth": 32,
                    "frameHeight": 32,
                    "startFrame": 0,
                    "endFrame": -1,
                    "spacing": 0,
                    "margin": 0
                },
                "type": "spritesheet",
                "key": "Winter_entities (16 x 16)"
            },
            {
                "url": "assets/Seasonal Tileset/4 - Winter World/Winter_entities (16 x 16).png",
                "type": "image",
                "key": "Winter_entities (16 x 16)_1"
            }
        ]
    },
    "meta": {
        "app": "Phaser Editor 2D - Asset Pack Editor",
        "contentType": "phasereditor2d.pack.core.AssetContentType",
        "url": "https://phasereditor2d.com",
        "version": 2,
        "showAllFilesInBlocks": false
    }
}